icestick/uart/mat_mul.v
module mat_mul(
    input [7:0] a11, a12, a21, a22,
    input [7:0] b11, b12, b21, b22,
    input clk,
    /* I know this allows overflow */
    output reg [7:0] c11, c12, c21, c22 
);

always @(posedge clk) begin
    c11 <= a11 * b11 + a12 * b21;
    c12 <= a11 * b12 + a12 * b22;
    c21 <= a21 * b11 + a22 * b21;
    c22 <= a21 * b12 + a22 * b22;
end

endmodule

icestick/uart/uart_tx.v
`default_nettype none

module uart_tx (
    input   wire      clk,
    output  wire      tx,
    input   [7:0] tx_byte,
    input   wire      tx_enable
);

    localparam  BAUD         = 115200;
    localparam  CLK_HZ       = 12000000;
    localparam  CLKS_IN_BAUD = CLK_HZ / BAUD;

    reg [1:0]   state;
    localparam  S_IDLE = 0;
    localparam  S_TX   = 1;
    localparam  S_STOP = 2;

    reg [6:0] counter;
    reg [1:0] state;
    reg [1:0] next_state;
    reg [3:0] tx_idx;
    wire      tick;
    assign    tick = counter >= CLKS_IN_BAUD;
    wire      packet_sent;
    assign    packet_sent = tx_idx > 9; /* start bit + 8 data bits + stop bit */

    initial begin
        counter    <= 0;
        state      <= S_IDLE;
        next_state <= S_IDLE;
        tx_idx     <= 0;
        tx         <= 1; /* normally high */
    end

    always @(negedge clk) begin
        case (state)
            S_IDLE: next_state <= tx_enable   ? S_TX   : S_IDLE;
            S_TX:   next_state <= packet_sent ? S_STOP : S_TX;
            S_STOP: next_state <= packet_sent ? S_STOP : S_IDLE;
        endcase
     end

     always @(posedge clk) begin
        state <= next_state;
     end

     always @(posedge clk) begin
        counter <= counter + 1;
        case (state)
            S_IDLE: begin
                counter <= 0; 
                tx_idx <= 0;
            end 

            S_TX: begin
                if (tick) begin
                    if (tx_idx == 0) begin                   /* start bit low */
                        tx <= 0;
                    end 
                    
                    else if (tx_idx > 0 && tx_idx < 9) begin /* payload bits */
                        tx <= tx_byte[tx_idx - 1];
                    end                       

                    else if (tx_idx == 9) begin              /* stop bit high */
                        tx <= 1;
                    end

                    counter <= 0;
                    tx_idx  <= tx_idx + 1;
                end
            end

            S_STOP: begin
                tx_idx <= 0;
                counter <= 0;
            end
        endcase
     end
endmodule

icestick/uart/uart_rx.v
`default_nettype none

module uart_rx (
    input  wire      clk,
    input  wire      rx,
    input  wire      rx_enable,
    output wire [7:0] rx_byte,
    output wire      byte_available
);

    localparam  BAUD         = 115200;
    localparam  CLK_HZ       = 12000000;
    localparam  CLKS_IN_BAUD = CLK_HZ / BAUD;

    localparam  S_IDLE       = 0;
    localparam  S_RX         = 1;
    localparam  S_STOP       = 2;

    reg [6:0] counter;
    reg [1:0] state;
    reg [1:0] next_state;
    reg [3:0] rx_idx;
    wire      tick;

    reg [7:0] _rx_byte;
    assign rx_byte = _rx_byte;
    
    assign    byte_available = rx_idx > 8;
    assign    tick           = counter >= CLKS_IN_BAUD;

    initial begin
        counter    <= 0;
        state      <= S_IDLE;
        next_state <= S_IDLE;
        rx_idx     <= 0;
    end

    /* Handle finite state machine flow */
    always @(negedge clk) begin
        case (state)
            S_IDLE: next_state <= rx_enable && ~rx ? S_RX   : S_IDLE;
            S_RX:   next_state <= byte_available   ? S_STOP : S_RX;
            S_STOP: next_state <= S_IDLE;
        endcase
    end

    always @(posedge clk) begin
        state <= next_state;
    end

    always @(posedge clk) begin
        counter <= counter + 1;
        case (state)
            S_IDLE: begin
                counter <= 0;  
                rx_idx  <= 0;        
            end

            S_RX: begin
                if (tick) begin
                    counter         <= 0;
                    _rx_byte[rx_idx] <= rx;
                    rx_idx          <= rx_idx + 1;
                end
            end

            S_STOP: begin
                counter <= 0;   
                rx_idx  <= 0;     
            end
        endcase        
    end
endmodule

icestick/uart/uart.v
`default_nettype none

module uart (
    input        clk,
    input        rx,
    output       tx,
    input  [7:0] tx_byte,
    output [7:0] rx_byte,
    input        tx_enable,
    input        rx_enable,
    output       byte_available
);

    uart_rx uart_rx (
        .clk(clk),
        .rx(rx),
        .rx_enable(rx_enable),
        .rx_byte(rx_byte),
        .byte_available(byte_available)
    );

    uart_tx uart_tx (
        .clk(clk),
        .tx(tx),
        .tx_enable(tx_enable),
        .tx_byte(tx_byte)
    );

endmodule

icestick/uart/top.v
`default_nettype none

module top(
    input      clk,
    input      rx,
    output     tx,
    // output reg D1,
    // output reg D2,
    output reg D5
);

    reg [23:0] counter;

    /* --- serial --- */

    wire [7:0] rx_byte;
    reg [7:0] tx_byte;
    reg [7:0] test_char;
    wire       byte_available;
    reg       tx_enable;
    reg       rx_enable;

    uart serial (
        .clk(clk),
        .rx(rx),
        .tx(tx),
        .tx_byte(tx_byte),
        .rx_byte(rx_byte),
        .tx_enable(tx_enable),
        .rx_enable(rx_enable),
        .byte_available(byte_available)
    );

    /* --- mat mul --- */

    reg [7:0]  _a11, _a12, _a21, _a22;
    wire [7:0]  a11,  a12,  a21,  a22;
    wire [7:0]  b11,  b12,  b21,  b22;
    reg [7:0]  _b11, _b12, _b21, _b22;
    assign a11 = _a11;
    assign a12 = _a12;
    assign a21 = _a21;
    assign a22 = _a22;
    assign b11 = _b11;
    assign b12 = _b12;
    assign b21 = _b21;
    assign b22 = _b22;

    wire [7:0]  c11, c12, c21, c22;
    reg [2:0]  matA_idx, matB_idx;
    reg [7:0]  current_job;
    reg        current_mat;
    localparam A = 0;
    localparam B = 1;

    mat_mul mat_mul (
        .clk(clk),
        .a11(a11), .a12(a12), .a21(a21), .a22(a22),
        .b11(b11), .b12(b12), .b21(b21), .b22(b22),
        .c11(c11), .c12(c12), .c21(c21), .c22(c22) 
    );

    /* --- fsm --- */

    reg [3:0]  state;
    reg [3:0]  next_state;
    localparam S_IDLE      = 0;
    localparam S_START     = 1;
    localparam S_CHECK_JOB = 2;
    localparam S_MAT_A     = 3;
    localparam S_MAT_B     = 4;
    localparam S_STOP      = 5;

    initial begin
        test_char      <= "0";
        counter        <= 0;
        rx_enable      <= 1;
        tx_enable      <= 0;
        state          <= S_IDLE;
        next_state     <= S_IDLE;
        current_mat    <= A;
    end

    always @(posedge clk) begin
        state <= next_state;
    end

    always @(posedge clk) begin
        rx_enable <= 1;
        counter <= counter + 1;

            case (state)

                /* ------ */

                S_IDLE: begin
                    if (byte_available) begin
                        rx_enable <= 0;
                        tx_byte <= rx_byte;
                        if (rx_byte == 8'hFF) begin
                            next_state <= S_START;
                        end
                    end
                end

                /* ------ */

                S_START: begin
                    if (byte_available) begin
                        rx_enable <= 0;
                        tx_byte <= rx_byte;
                        if (rx_byte == 8'h00) begin
                            current_mat <= A;
                            next_state <= S_CHECK_JOB;
                        end else if (rx_byte == 8'h01) begin
                            current_mat <= B;
                            next_state <= S_CHECK_JOB;
                        end else begin
                            next_state <= S_IDLE;
                        end
                    end
                end

                /* ------ */

                S_CHECK_JOB: begin
                    if (byte_available) begin
                        rx_enable <= 0;
                        tx_byte <= rx_byte;
                        if (current_mat == A) begin
                            current_job <= rx_byte;
                            next_state <= S_MAT_A;
                        end 
                        
                        else if (current_mat == B) begin
                            if (current_job == rx_byte) begin
                                next_state <= S_MAT_B;
                            end else begin
                                next_state <= S_IDLE;
                            end    
                        end
                    end
                end

                /* ------ */

                S_MAT_A: begin
                    if (byte_available) begin
                        rx_enable <= 0;
                        tx_byte <= rx_byte;
                        case (matA_idx)
                            0: _a11 <= rx_byte;
                            1: _a12 <= rx_byte;
                            2: _a21 <= rx_byte;
                            3: _a22 <= rx_byte;
                            default: begin
                                next_state  <= S_IDLE; /* start next mat */
                            end 
                        endcase

                        matA_idx <= matA_idx + 1;
                    end

                    else begin /* restart if no byte available... */
                        next_state <= S_IDLE;
                    end
                end
                
                /* ------ */
                
                S_MAT_B: begin
                            D5 = ~D5;
                    if (byte_available) begin
                        case (matB_idx)
                            0: _b11 <= rx_byte;
                            1: _b12 <= rx_byte;
                            2: _b21 <= rx_byte;
                            3: _b22 <= rx_byte;
                            default: begin
                                next_state <= S_STOP; /* start next mat */
                                current_mat <= A;
                            end
                        endcase

                        matB_idx <= matB_idx + 1;
                    end

                    else begin /* restart if no byte available... */
                        next_state <= S_IDLE;
                        current_mat <= A;
                    end
                end
            endcase

        // if (counter >= 12_000_00) begin
        //     rx_enable <= 0;
        //     D5 <= ~D5;
        //     tx_byte   <= test_char;   
        //     counter   <= 0;       
        // end else begin
        //     rx_enable <= 1;
        // end
    end
endmodule

icestick/uart/top_tb.v
`timescale 1ns / 1ps

module tb_top();

    reg clk = 0;
    reg rx = 1;
    wire tx;

    top uut(
        .clk(clk),
        .rx(rx),
        .tx(tx)
    );

    // Clock generation
    always #41.6667 clk = !clk; // 12 MHz clock

    // Stimulus
    initial begin
        $dumpfile("tb_top.vcd");
        $dumpvars(0, tb_top);

        // Send bytes with start and stop bits at 115200 baud
        send_byte(8'hFF);
        send_byte(8'h00);
        send_byte(8'h11);
        send_byte(8'h01);
        send_byte(8'h02);
        send_byte(8'h03);
        send_byte(8'h04);

        #1000;
        $finish;
    end

    // Function to send a byte including start and stop bits
    task send_byte;
        input [7:0] data;
        integer i;
        begin
            rx = 0; // Start bit
            #8680; // One bit time (1/115200 s)
            for (i = 0; i < 8; i = i + 1) begin
                rx = data[i];
                #8680;
            end
            rx = 1; // Stop bit
            #8680; // Stop bit time
        end
    endtask

endmodule

icestick/uart/top_tb.vcd
$date
	Mon Sep  9 22:19:21 2024
$end
$version
	Icarus Verilog
$end
$timescale
	1ps
$end
$scope module tb_top $end
$var wire 1 ! tx $end
$var reg 1 " clk $end
$var reg 1 # rx $end
$scope module uut $end
$var wire 8 $ a11 [7:0] $end
$var wire 8 % a12 [7:0] $end
$var wire 8 & a21 [7:0] $end
$var wire 8 ' a22 [7:0] $end
$var wire 8 ( b11 [7:0] $end
$var wire 8 ) b12 [7:0] $end
$var wire 8 * b21 [7:0] $end
$var wire 8 + b22 [7:0] $end
$var wire 1 " clk $end
$var wire 1 # rx $end
$var wire 1 ! tx $end
$var wire 8 , rx_byte [7:0] $end
$var wire 8 - c22 [7:0] $end
$var wire 8 . c21 [7:0] $end
$var wire 8 / c12 [7:0] $end
$var wire 8 0 c11 [7:0] $end
$var wire 1 1 byte_available $end
$var reg 1 2 D5 $end
$var reg 8 3 _a11 [7:0] $end
$var reg 8 4 _a12 [7:0] $end
$var reg 8 5 _a21 [7:0] $end
$var reg 8 6 _a22 [7:0] $end
$var reg 8 7 _b11 [7:0] $end
$var reg 8 8 _b12 [7:0] $end
$var reg 8 9 _b21 [7:0] $end
$var reg 8 : _b22 [7:0] $end
$var reg 24 ; counter [23:0] $end
$var reg 8 < current_job [7:0] $end
$var reg 1 = current_mat $end
$var reg 3 > matA_idx [2:0] $end
$var reg 3 ? matB_idx [2:0] $end
$var reg 4 @ next_state [3:0] $end
$var reg 1 A rx_enable $end
$var reg 4 B state [3:0] $end
$var reg 8 C test_char [7:0] $end
$var reg 8 D tx_byte [7:0] $end
$var reg 1 E tx_enable $end
$scope module mat_mul $end
$var wire 8 F a11 [7:0] $end
$var wire 8 G a12 [7:0] $end
$var wire 8 H a21 [7:0] $end
$var wire 8 I a22 [7:0] $end
$var wire 8 J b11 [7:0] $end
$var wire 8 K b12 [7:0] $end
$var wire 8 L b21 [7:0] $end
$var wire 8 M b22 [7:0] $end
$var wire 1 " clk $end
$var reg 8 N c11 [7:0] $end
$var reg 8 O c12 [7:0] $end
$var reg 8 P c21 [7:0] $end
$var reg 8 Q c22 [7:0] $end
$upscope $end
$scope module serial $end
$var wire 1 " clk $end
$var wire 1 # rx $end
$var wire 1 A rx_enable $end
$var wire 8 R tx_byte [7:0] $end
$var wire 1 E tx_enable $end
$var wire 1 ! tx $end
$var wire 8 S rx_byte [7:0] $end
$var wire 1 1 byte_available $end
$scope module uart_rx $end
$var wire 1 " clk $end
$var wire 1 # rx $end
$var wire 8 T rx_byte [7:0] $end
$var wire 1 A rx_enable $end
$var wire 1 U tick $end
$var wire 1 1 byte_available $end
$var reg 8 V _rx_byte [7:0] $end
$var reg 7 W counter [6:0] $end
$var reg 2 X next_state [1:0] $end
$var reg 4 Y rx_idx [3:0] $end
$var reg 2 Z state [1:0] $end
$upscope $end
$scope module uart_tx $end
$var wire 1 " clk $end
$var wire 8 [ tx_byte [7:0] $end
$var wire 1 E tx_enable $end
$var wire 1 \ tick $end
$var wire 1 ] packet_sent $end
$var reg 7 ^ counter [6:0] $end
$var reg 2 _ next_state [1:0] $end
$var reg 2 ` state [1:0] $end
$var reg 1 ! tx $end
$var reg 4 a tx_idx [3:0] $end
$upscope $end
$upscope $end
$upscope $end
$scope task send_byte $end
$var reg 8 b data [7:0] $end
$var integer 32 c i [31:0] $end
$upscope $end
$upscope $end
$enddefinitions $end
#0
$dumpvars
bx c
b11111111 b
b0 a
b0 `
b0 _
b0 ^
0]
0\
bx [
b0 Z
b0 Y
b0 X
b0 W
bx V
0U
bx T
bx S
bx R
bx Q
bx P
bx O
bx N
bx M
bx L
bx K
bx J
bx I
bx H
bx G
bx F
0E
bx D
b110000 C
b0 B
1A
b0 @
bx ?
bx >
0=
bx <
b0 ;
bx :
bx 9
bx 8
bx 7
bx 6
bx 5
bx 4
bx 3
x2
01
bx 0
bx /
bx .
bx -
bx ,
bx +
bx *
bx )
bx (
bx '
bx &
bx %
bx $
0#
0"
1!
$end
#41667
b0 W
b0 ^
b1 ;
1"
#83334
b1 X
0"
#125001
b10 ;
b0 ^
b0 W
b1 Z
1"
#166668
0"
#208335
b1 W
b0 ^
b11 ;
1"
#250002
0"
#291669
b100 ;
b0 ^
b10 W
1"
#333336
0"
#375003
b11 W
b0 ^
b101 ;
1"
#416670
0"
#458337
b110 ;
b0 ^
b100 W
1"
#500004
0"
#541671
b101 W
b0 ^
b111 ;
1"
#583338
0"
#625005
b1000 ;
b0 ^
b110 W
1"
#666672
0"
#708339
b111 W
b0 ^
b1001 ;
1"
#750006
0"
#791673
b1010 ;
b0 ^
b1000 W
1"
#833340
0"
#875007
b1001 W
b0 ^
b1011 ;
1"
#916674
0"
#958341
b1100 ;
b0 ^
b1010 W
1"
#1000008
0"
#1041675
b1011 W
b0 ^
b1101 ;
1"
#1083342
0"
#1125009
b1110 ;
b0 ^
b1100 W
1"
#1166676
0"
#1208343
b1101 W
b0 ^
b1111 ;
1"
#1250010
0"
#1291677
b10000 ;
b0 ^
b1110 W
1"
#1333344
0"
#1375011
b1111 W
b0 ^
b10001 ;
1"
#1416678
0"
#1458345
b10010 ;
b0 ^
b10000 W
1"
#1500012
0"
#1541679
b10001 W
b0 ^
b10011 ;
1"
#1583346
0"
#1625013
b10100 ;
b0 ^
b10010 W
1"
#1666680
0"
#1708347
b10011 W
b0 ^
b10101 ;
1"
#1750014
0"
#1791681
b10110 ;
b0 ^
b10100 W
1"
#1833348
0"
#1875015
b10101 W
b0 ^
b10111 ;
1"
#1916682
0"
#1958349
b11000 ;
b0 ^
b10110 W
1"
#2000016
0"
#2041683
b10111 W
b0 ^
b11001 ;
1"
#2083350
0"
#2125017
b11010 ;
b0 ^
b11000 W
1"
#2166684
0"
#2208351
b11001 W
b0 ^
b11011 ;
1"
#2250018
0"
#2291685
b11100 ;
b0 ^
b11010 W
1"
#2333352
0"
#2375019
b11011 W
b0 ^
b11101 ;
1"
#2416686
0"
#2458353
b11110 ;
b0 ^
b11100 W
1"
#2500020
0"
#2541687
b11101 W
b0 ^
b11111 ;
1"
#2583354
0"
#2625021
b100000 ;
b0 ^
b11110 W
1"
#2666688
0"
#2708355
b11111 W
b0 ^
b100001 ;
1"
#2750022
0"
#2791689
b100010 ;
b0 ^
b100000 W
1"
#2833356
0"
#2875023
b100001 W
b0 ^
b100011 ;
1"
#2916690
0"
#2958357
b100100 ;
b0 ^
b100010 W
1"
#3000024
0"
#3041691
b100011 W
b0 ^
b100101 ;
1"
#3083358
0"
#3125025
b100110 ;
b0 ^
b100100 W
1"
#3166692
0"
#3208359
b100101 W
b0 ^
b100111 ;
1"
#3250026
0"
#3291693
b101000 ;
b0 ^
b100110 W
1"
#3333360
0"
#3375027
b100111 W
b0 ^
b101001 ;
1"
#3416694
0"
#3458361
b101010 ;
b0 ^
b101000 W
1"
#3500028
0"
#3541695
b101001 W
b0 ^
b101011 ;
1"
#3583362
0"
#3625029
b101100 ;
b0 ^
b101010 W
1"
#3666696
0"
#3708363
b101011 W
b0 ^
b101101 ;
1"
#3750030
0"
#3791697
b101110 ;
b0 ^
b101100 W
1"
#3833364
0"
#3875031
b101101 W
b0 ^
b101111 ;
1"
#3916698
0"
#3958365
b110000 ;
b0 ^
b101110 W
1"
#4000032
0"
#4041699
b101111 W
b0 ^
b110001 ;
1"
#4083366
0"
#4125033
b110010 ;
b0 ^
b110000 W
1"
#4166700
0"
#4208367
b110001 W
b0 ^
b110011 ;
1"
#4250034
0"
#4291701
b110100 ;
b0 ^
b110010 W
1"
#4333368
0"
#4375035
b110011 W
b0 ^
b110101 ;
1"
#4416702
0"
#4458369
b110110 ;
b0 ^
b110100 W
1"
#4500036
0"
#4541703
b110101 W
b0 ^
b110111 ;
1"
#4583370
0"
#4625037
b111000 ;
b0 ^
b110110 W
1"
#4666704
0"
#4708371
b110111 W
b0 ^
b111001 ;
1"
#4750038
0"
#4791705
b111010 ;
b0 ^
b111000 W
1"
#4833372
0"
#4875039
b111001 W
b0 ^
b111011 ;
1"
#4916706
0"
#4958373
b111100 ;
b0 ^
b111010 W
1"
#5000040
0"
#5041707
b111011 W
b0 ^
b111101 ;
1"
#5083374
0"
#5125041
b111110 ;
b0 ^
b111100 W
1"
#5166708
0"
#5208375
b111101 W
b0 ^
b111111 ;
1"
#5250042
0"
#5291709
b1000000 ;
b0 ^
b111110 W
1"
#5333376
0"
#5375043
b111111 W
b0 ^
b1000001 ;
1"
#5416710
0"
#5458377
b1000010 ;
b0 ^
b1000000 W
1"
#5500044
0"
#5541711
b1000001 W
b0 ^
b1000011 ;
1"
#5583378
0"
#5625045
b1000100 ;
b0 ^
b1000010 W
1"
#5666712
0"
#5708379
b1000011 W
b0 ^
b1000101 ;
1"
#5750046
0"
#5791713
b1000110 ;
b0 ^
b1000100 W
1"
#5833380
0"
#5875047
b1000101 W
b0 ^
b1000111 ;
1"
#5916714
0"
#5958381
b1001000 ;
b0 ^
b1000110 W
1"
#6000048
0"
#6041715
b1000111 W
b0 ^
b1001001 ;
1"
#6083382
0"
#6125049
b1001010 ;
b0 ^
b1001000 W
1"
#6166716
0"
#6208383
b1001001 W
b0 ^
b1001011 ;
1"
#6250050
0"
#6291717
b1001100 ;
b0 ^
b1001010 W
1"
#6333384
0"
#6375051
b1001011 W
b0 ^
b1001101 ;
1"
#6416718
0"
#6458385
b1001110 ;
b0 ^
b1001100 W
1"
#6500052
0"
#6541719
b1001101 W
b0 ^
b1001111 ;
1"
#6583386
0"
#6625053
b1010000 ;
b0 ^
b1001110 W
1"
#6666720
0"
#6708387
b1001111 W
b0 ^
b1010001 ;
1"
#6750054
0"
#6791721
b1010010 ;
b0 ^
b1010000 W
1"
#6833388
0"
#6875055
b1010001 W
b0 ^
b1010011 ;
1"
#6916722
0"
#6958389
b1010100 ;
b0 ^
b1010010 W
1"
#7000056
0"
#7041723
b1010011 W
b0 ^
b1010101 ;
1"
#7083390
0"
#7125057
b1010110 ;
b0 ^
b1010100 W
1"
#7166724
0"
#7208391
b1010101 W
b0 ^
b1010111 ;
1"
#7250058
0"
#7291725
b1011000 ;
b0 ^
b1010110 W
1"
#7333392
0"
#7375059
b1010111 W
b0 ^
b1011001 ;
1"
#7416726
0"
#7458393
b1011010 ;
b0 ^
b1011000 W
1"
#7500060
0"
#7541727
b1011001 W
b0 ^
b1011011 ;
1"
#7583394
0"
#7625061
b1011100 ;
b0 ^
b1011010 W
1"
#7666728
0"
#7708395
b1011011 W
b0 ^
b1011101 ;
1"
#7750062
0"
#7791729
b1011110 ;
b0 ^
b1011100 W
1"
#7833396
0"
#7875063
b1011101 W
b0 ^
b1011111 ;
1"
#7916730
0"
#7958397
b1100000 ;
b0 ^
b1011110 W
1"
#8000064
0"
#8041731
b1011111 W
b0 ^
b1100001 ;
1"
#8083398
0"
#8125065
b1100010 ;
b0 ^
b1100000 W
1"
#8166732
0"
#8208399
b1100001 W
b0 ^
b1100011 ;
1"
#8250066
0"
#8291733
b1100100 ;
b0 ^
b1100010 W
1"
#8333400
0"
#8375067
b1100011 W
b0 ^
b1100101 ;
1"
#8416734
0"
#8458401
b1100110 ;
b0 ^
b1100100 W
1"
#8500068
0"
#8541735
b1100101 W
b0 ^
b1100111 ;
1"
#8583402
0"
#8625069
b1101000 ;
b0 ^
b1100110 W
1"
#8666736
0"
#8680000
1#
b0 c
#8708403
b1100111 W
b0 ^
b1101001 ;
1"
#8750070
0"
#8791737
b1101010 ;
b0 ^
1U
b1101000 W
1"
#8833404
0"
#8875071
b1 Y
bx1 ,
bx1 S
bx1 T
bx1 V
0U
b0 W
b0 ^
b1101011 ;
1"
#8916738
0"
#8958405
b1101100 ;
b0 ^
b1 W
1"
#9000072
0"
#9041739
b10 W
b0 ^
b1101101 ;
1"
#9083406
0"
#9125073
b1101110 ;
b0 ^
b11 W
1"
#9166740
0"
#9208407
b100 W
b0 ^
b1101111 ;
1"
#9250074
0"
#9291741
b1110000 ;
b0 ^
b101 W
1"
#9333408
0"
#9375075
b110 W
b0 ^
b1110001 ;
1"
#9416742
0"
#9458409
b1110010 ;
b0 ^
b111 W
1"
#9500076
0"
#9541743
b1000 W
b0 ^
b1110011 ;
1"
#9583410
0"
#9625077
b1110100 ;
b0 ^
b1001 W
1"
#9666744
0"
#9708411
b1010 W
b0 ^
b1110101 ;
1"
#9750078
0"
#9791745
b1110110 ;
b0 ^
b1011 W
1"
#9833412
0"
#9875079
b1100 W
b0 ^
b1110111 ;
1"
#9916746
0"
#9958413
b1111000 ;
b0 ^
b1101 W
1"
#10000080
0"
#10041747
b1110 W
b0 ^
b1111001 ;
1"
#10083414
0"
#10125081
b1111010 ;
b0 ^
b1111 W
1"
#10166748
0"
#10208415
b10000 W
b0 ^
b1111011 ;
1"
#10250082
0"
#10291749
b1111100 ;
b0 ^
b10001 W
1"
#10333416
0"
#10375083
b10010 W
b0 ^
b1111101 ;
1"
#10416750
0"
#10458417
b1111110 ;
b0 ^
b10011 W
1"
#10500084
0"
#10541751
b10100 W
b0 ^
b1111111 ;
1"
#10583418
0"
#10625085
b10000000 ;
b0 ^
b10101 W
1"
#10666752
0"
#10708419
b10110 W
b0 ^
b10000001 ;
1"
#10750086
0"
#10791753
b10000010 ;
b0 ^
b10111 W
1"
#10833420
0"
#10875087
b11000 W
b0 ^
b10000011 ;
1"
#10916754
0"
#10958421
b10000100 ;
b0 ^
b11001 W
1"
#11000088
0"
#11041755
b11010 W
b0 ^
b10000101 ;
1"
#11083422
0"
#11125089
b10000110 ;
b0 ^
b11011 W
1"
#11166756
0"
#11208423
b11100 W
b0 ^
b10000111 ;
1"
#11250090
0"
#11291757
b10001000 ;
b0 ^
b11101 W
1"
#11333424
0"
#11375091
b11110 W
b0 ^
b10001001 ;
1"
#11416758
0"
#11458425
b10001010 ;
b0 ^
b11111 W
1"
#11500092
0"
#11541759
b100000 W
b0 ^
b10001011 ;
1"
#11583426
0"
#11625093
b10001100 ;
b0 ^
b100001 W
1"
#11666760
0"
#11708427
b100010 W
b0 ^
b10001101 ;
1"
#11750094
0"
#11791761
b10001110 ;
b0 ^
b100011 W
1"
#11833428
0"
#11875095
b100100 W
b0 ^
b10001111 ;
1"
#11916762
0"
#11958429
b10010000 ;
b0 ^
b100101 W
1"
#12000096
0"
#12041763
b100110 W
b0 ^
b10010001 ;
1"
#12083430
0"
#12125097
b10010010 ;
b0 ^
b100111 W
1"
#12166764
0"
#12208431
b101000 W
b0 ^
b10010011 ;
1"
#12250098
0"
#12291765
b10010100 ;
b0 ^
b101001 W
1"
#12333432
0"
#12375099
b101010 W
b0 ^
b10010101 ;
1"
#12416766
0"
#12458433
b10010110 ;
b0 ^
b101011 W
1"
#12500100
0"
#12541767
b101100 W
b0 ^
b10010111 ;
1"
#12583434
0"
#12625101
b10011000 ;
b0 ^
b101101 W
1"
#12666768
0"
#12708435
b101110 W
b0 ^
b10011001 ;
1"
#12750102
0"
#12791769
b10011010 ;
b0 ^
b101111 W
1"
#12833436
0"
#12875103
b110000 W
b0 ^
b10011011 ;
1"
#12916770
0"
#12958437
b10011100 ;
b0 ^
b110001 W
1"
#13000104
0"
#13041771
b110010 W
b0 ^
b10011101 ;
1"
#13083438
0"
#13125105
b10011110 ;
b0 ^
b110011 W
1"
#13166772
0"
#13208439
b110100 W
b0 ^
b10011111 ;
1"
#13250106
0"
#13291773
b10100000 ;
b0 ^
b110101 W
1"
#13333440
0"
#13375107
b110110 W
b0 ^
b10100001 ;
1"
#13416774
0"
#13458441
b10100010 ;
b0 ^
b110111 W
1"
#13500108
0"
#13541775
b111000 W
b0 ^
b10100011 ;
1"
#13583442
0"
#13625109
b10100100 ;
b0 ^
b111001 W
1"
#13666776
0"
#13708443
b111010 W
b0 ^
b10100101 ;
1"
#13750110
0"
#13791777
b10100110 ;
b0 ^
b111011 W
1"
#13833444
0"
#13875111
b111100 W
b0 ^
b10100111 ;
1"
#13916778
0"
#13958445
b10101000 ;
b0 ^
b111101 W
1"
#14000112
0"
#14041779
b111110 W
b0 ^
b10101001 ;
1"
#14083446
0"
#14125113
b10101010 ;
b0 ^
b111111 W
1"
#14166780
0"
#14208447
b1000000 W
b0 ^
b10101011 ;
1"
#14250114
0"
#14291781
b10101100 ;
b0 ^
b1000001 W
1"
#14333448
0"
#14375115
b1000010 W
b0 ^
b10101101 ;
1"
#14416782
0"
#14458449
b10101110 ;
b0 ^
b1000011 W
1"
#14500116
0"
#14541783
b1000100 W
b0 ^
b10101111 ;
1"
#14583450
0"
#14625117
b10110000 ;
b0 ^
b1000101 W
1"
#14666784
0"
#14708451
b1000110 W
b0 ^
b10110001 ;
1"
#14750118
0"
#14791785
b10110010 ;
b0 ^
b1000111 W
1"
#14833452
0"
#14875119
b1001000 W
b0 ^
b10110011 ;
1"
#14916786
0"
#14958453
b10110100 ;
b0 ^
b1001001 W
1"
#15000120
0"
#15041787
b1001010 W
b0 ^
b10110101 ;
1"
#15083454
0"
#15125121
b10110110 ;
b0 ^
b1001011 W
1"
#15166788
0"
#15208455
b1001100 W
b0 ^
b10110111 ;
1"
#15250122
0"
#15291789
b10111000 ;
b0 ^
b1001101 W
1"
#15333456
0"
#15375123
b1001110 W
b0 ^
b10111001 ;
1"
#15416790
0"
#15458457
b10111010 ;
b0 ^
b1001111 W
1"
#15500124
0"
#15541791
b1010000 W
b0 ^
b10111011 ;
1"
#15583458
0"
#15625125
b10111100 ;
b0 ^
b1010001 W
1"
#15666792
0"
#15708459
b1010010 W
b0 ^
b10111101 ;
1"
#15750126
0"
#15791793
b10111110 ;
b0 ^
b1010011 W
1"
#15833460
0"
#15875127
b1010100 W
b0 ^
b10111111 ;
1"
#15916794
0"
#15958461
b11000000 ;
b0 ^
b1010101 W
1"
#16000128
0"
#16041795
b1010110 W
b0 ^
b11000001 ;
1"
#16083462
0"
#16125129
b11000010 ;
b0 ^
b1010111 W
1"
#16166796
0"
#16208463
b1011000 W
b0 ^
b11000011 ;
1"
#16250130
0"
#16291797
b11000100 ;
b0 ^
b1011001 W
1"
#16333464
0"
#16375131
b1011010 W
b0 ^
b11000101 ;
1"
#16416798
0"
#16458465
b11000110 ;
b0 ^
b1011011 W
1"
#16500132
0"
#16541799
b1011100 W
b0 ^
b11000111 ;
1"
#16583466
0"
#16625133
b11001000 ;
b0 ^
b1011101 W
1"
#16666800
0"
#16708467
b1011110 W
b0 ^
b11001001 ;
1"
#16750134
0"
#16791801
b11001010 ;
b0 ^
b1011111 W
1"
#16833468
0"
#16875135
b1100000 W
b0 ^
b11001011 ;
1"
#16916802
0"
#16958469
b11001100 ;
b0 ^
b1100001 W
1"
#17000136
0"
#17041803
b1100010 W
b0 ^
b11001101 ;
1"
#17083470
0"
#17125137
b11001110 ;
b0 ^
b1100011 W
1"
#17166804
0"
#17208471
b1100100 W
b0 ^
b11001111 ;
1"
#17250138
0"
#17291805
b11010000 ;
b0 ^
b1100101 W
1"
#17333472
0"
#17360000
b1 c
#17375139
b1100110 W
b0 ^
b11010001 ;
1"
#17416806
0"
#17458473
b11010010 ;
b0 ^
b1100111 W
1"
#17500140
0"
#17541807
1U
b1101000 W
b0 ^
b11010011 ;
1"
#17583474
0"
#17625141
b11010100 ;
b0 ^
b10 Y
bx11 ,
bx11 S
bx11 T
bx11 V
0U
b0 W
1"
#17666808
0"
#17708475
b1 W
b0 ^
b11010101 ;
1"
#17750142
0"
#17791809
b11010110 ;
b0 ^
b10 W
1"
#17833476
0"
#17875143
b11 W
b0 ^
b11010111 ;
1"
#17916810
0"
#17958477
b11011000 ;
b0 ^
b100 W
1"
#18000144
0"
#18041811
b101 W
b0 ^
b11011001 ;
1"
#18083478
0"
#18125145
b11011010 ;
b0 ^
b110 W
1"
#18166812
0"
#18208479
b111 W
b0 ^
b11011011 ;
1"
#18250146
0"
#18291813
b11011100 ;
b0 ^
b1000 W
1"
#18333480
0"
#18375147
b1001 W
b0 ^
b11011101 ;
1"
#18416814
0"
#18458481
b11011110 ;
b0 ^
b1010 W
1"
#18500148
0"
#18541815
b1011 W
b0 ^
b11011111 ;
1"
#18583482
0"
#18625149
b11100000 ;
b0 ^
b1100 W
1"
#18666816
0"
#18708483
b1101 W
b0 ^
b11100001 ;
1"
#18750150
0"
#18791817
b11100010 ;
b0 ^
b1110 W
1"
#18833484
0"
#18875151
b1111 W
b0 ^
b11100011 ;
1"
#18916818
0"
#18958485
b11100100 ;
b0 ^
b10000 W
1"
#19000152
0"
#19041819
b10001 W
b0 ^
b11100101 ;
1"
#19083486
0"
